integration/__init__.py
integration/test_client.py
twisted/plugins/txacme_endpoint.py
txacme/__init__.py
txacme/_endpoint_parser.py
txacme/_version.py
txacme/client.py
txacme/endpoint.py
txacme/errors.py
txacme/interfaces.py
txacme/logging.py
txacme/messages.py
txacme/service.py
txacme/store.py
txacme/testing.py
txacme/urls.py
txacme/util.py
txacme/challenges/__init__.py
txacme/challenges/_http.py
txacme/challenges/_libcloud.py
txacme/challenges/_tls.py
txacme/test/__init__.py
txacme/test/doubles.py
txacme/test/matchers.py
txacme/test/strategies.py
txacme/test/test_challenges.py
txacme/test/test_client.py
txacme/test/test_endpoint.py
txacme/test/test_matchers.py
txacme/test/test_service.py
txacme/test/test_store.py
txacme/test/test_util.py
txacme-0.9.3.dist-info/LICENSE
txacme-0.9.3.dist-info/METADATA
txacme-0.9.3.dist-info/WHEEL
txacme-0.9.3.dist-info/top_level.txt
txacme-0.9.3.dist-info/zip-safe
txacme-0.9.3.dist-info/RECORD
