Metadata-Version: 2.1
Name: txacme
Version: 0.9.3
Summary: ACME protocol implementation for Twisted
Home-page: https://github.com/mithrandi/txacme
Author: Tristan Seligmann
Author-email: mithrandi@mithrandi.net
Maintainer: Tristan Seligmann
Maintainer-email: mithrandi@mithrandi.net
License: Expat
Platform: UNKNOWN
Classifier: Development Status :: 3 - Alpha
Classifier: Intended Audience :: Developers
Classifier: Natural Language :: English
Classifier: License :: OSI Approved :: MIT License
Classifier: Operating System :: OS Independent
Classifier: Programming Language :: Python
Classifier: Programming Language :: Python :: 2
Classifier: Programming Language :: Python :: 2.7
Classifier: Programming Language :: Python :: 3
Classifier: Programming Language :: Python :: 3.4
Classifier: Programming Language :: Python :: 3.5
Classifier: Programming Language :: Python :: 3.6
Classifier: Programming Language :: Python :: 3.7
Classifier: Programming Language :: Python :: Implementation :: CPython
Classifier: Programming Language :: Python :: Implementation :: PyPy
Classifier: Topic :: Software Development :: Libraries :: Python Modules
Requires-Dist: acme (<1.0.0,>=0.21.0)
Requires-Dist: attrs (>=17.4.0)
Requires-Dist: eliot (>=0.8.0)
Requires-Dist: josepy
Requires-Dist: pem (>=16.1.0)
Requires-Dist: treq (>=15.1.0)
Requires-Dist: twisted[tls] (>=16.2.0)
Requires-Dist: txsni
Requires-Dist: pyopenssl (>=17.1.0)
Provides-Extra: libcloud
Requires-Dist: apache-libcloud ; extra == 'libcloud'
Provides-Extra: test
Requires-Dist: fixtures (>=1.4.0) ; extra == 'test'
Requires-Dist: hypothesis (<5.0.0,>=4.0.0) ; extra == 'test'
Requires-Dist: service-identity (>=17.0.0) ; extra == 'test'
Requires-Dist: testrepository (>=0.0.20) ; extra == 'test'
Requires-Dist: testscenarios ; extra == 'test'
Requires-Dist: testtools (>=2.1.0) ; extra == 'test'
